coin_test/__init__.py
coin_test/analysis/__init__.py
coin_test/analysis/tear_sheet.py
coin_test/backtest/__init__.py
coin_test/backtest/backtest_results.py
coin_test/backtest/market.py
coin_test/backtest/portfolio.py
coin_test/backtest/simulator.py
coin_test/backtest/strategy.py
coin_test/backtest/trade.py
coin_test/backtest/trade_request.py
coin_test/data/__init__.py
coin_test/data/composer.py
coin_test/data/datasaver.py
coin_test/data/dataset_generator.py
coin_test/data/datasets.py
coin_test/data/metadata.py
coin_test/data/processors.py
coin_test/orchestration/__init__.py
coin_test/orchestration/orchestration.py
coin_test/util/__init__.py
coin_test/util/enums.py
coin_test/util/money.py
coin_test/util/ticker.py
coin_test-0.1.0.dist-info/LICENSE
coin_test-0.1.0.dist-info/METADATA
coin_test-0.1.0.dist-info/WHEEL
coin_test-0.1.0.dist-info/RECORD
