Metadata-Version: 2.1
Name: coin-test
Version: 0.1.0
Summary: Robust and rigorous backtesting framework for cryptocurrencies.
Home-page: https://github.com/coin-test/coin-test
License: MIT
Keywords: cryptocurrency,backtesting
Author: Eamon Ito-Fisher
Author-email: eamon@itofisher.com
Requires-Python: >=3.10,<3.11
Classifier: License :: OSI Approved :: MIT License
Classifier: Programming Language :: Python :: 3
Classifier: Programming Language :: Python :: 3.10
Requires-Dist: croniter (>=1.3.7,<2.0.0)
Requires-Dist: pandas (>=1.5.0,<2.0.0)
Requires-Dist: pandas-stubs (>=1.5.3.230203,<2.0.0.0)
Requires-Dist: pytest-sugar (>=0.9.6,<0.10.0)
Requires-Dist: tqdm (>=4.64.1,<5.0.0)
Project-URL: Repository, https://github.com/coin-test/coin-test
